sklesion/__init__.py
sklesion/cl_info.pkl
sklesion/cr_test.pkl
sklesion/model.keras
sklesion/model.py
sklesion/model_props.pkl
sklesion/prob_to_label.py
sklesion-0.2.2.dist-info/METADATA
sklesion-0.2.2.dist-info/WHEEL
sklesion-0.2.2.dist-info/top_level.txt
sklesion-0.2.2.dist-info/RECORD
