Metadata-Version: 2.1
Name: sklesion
Version: 0.2.2
Summary: A Keras model for diagnosing skin lesions.
Author: Elio Pereira
Author-email: eliocpereira@hotmail.com
License: MIT
Classifier: Programming Language :: Python :: 3
Classifier: License :: OSI Approved :: MIT License
Classifier: Operating System :: OS Independent
Requires-Python: >=3.11
Requires-Dist: tensorflow==2.17.0
Requires-Dist: pandas==2.2.3
Requires-Dist: numpy==1.26.4
